chronqc/__init__.py
chronqc/_version.py
chronqc/chronqc.py
chronqc/chronqc_annotation.py
chronqc/chronqc_crongen.py
chronqc/chronqc_db.py
chronqc/chronqc_plot.py
chronqc/dev.py
chronqc/utils.py
chronqc/config/CET_config.json
chronqc/config/NGS_config.json
chronqc/config/PCR_config.json
chronqc/config/chronqc.conf
chronqc/config/crongen_config.ini
chronqc/db/chronqc.annotations.db
chronqc/templates/absolute_threshold.txt
chronqc/templates/bar_line_plot.txt
chronqc/templates/base_template.html
chronqc/templates/box_whisker_plot.txt
chronqc/templates/html.txt
chronqc/templates/mean_and_stdev.txt
chronqc/templates/percent_plot_threshold.txt
chronqc/templates/sidebar.txt
chronqc/templates/stacked_bar_plot.txt
chronqc-1.0.4.dist-info/DESCRIPTION.rst
chronqc-1.0.4.dist-info/METADATA
chronqc-1.0.4.dist-info/RECORD
chronqc-1.0.4.dist-info/WHEEL
chronqc-1.0.4.dist-info/entry_points.txt
chronqc-1.0.4.dist-info/metadata.json
chronqc-1.0.4.dist-info/top_level.txt
