Metadata-Version: 2.0
Name: chronqc
Version: 1.0.4
Summary: A Quality Control Monitoring System for Clinical Next Generation Sequencing
Home-page: https://github.com/nilesh-tawari/ChronQC
Author: Nilesh R. Tawari
Author-email: tawari.nilesh@gmail.com
License: MIT
Platform: UNKNOWN
Classifier: Development Status :: 4 - Beta
Classifier: Environment :: Console
Classifier: Intended Audience :: Science/Research
Classifier: License :: OSI Approved :: MIT License
Classifier: Natural Language :: English
Classifier: Operating System :: MacOS :: MacOS X
Classifier: Operating System :: POSIX
Classifier: Operating System :: Unix
Classifier: Topic :: Scientific/Engineering
Classifier: Topic :: Scientific/Engineering :: Bio-Informatics
Classifier: Topic :: Scientific/Engineering :: Visualization
Classifier: Programming Language :: JavaScript
Classifier: Programming Language :: Python :: 2.7
Classifier: Programming Language :: Python :: 3
Classifier: Programming Language :: Python :: 3.3
Classifier: Programming Language :: Python :: 3.4
Classifier: Programming Language :: Python :: 3.5
Requires-Dist: bottle
Requires-Dist: matplotlib
Requires-Dist: numpy
Requires-Dist: pandas (>=0.20.2)
